{"n":"Furniture and Furnishings","f":{"56100000":{"n":"Accommodation furniture","c":{"56101500":{"n":"Furniture","d":{"56101501":{"n":"Stands","s":false},"56101502":{"n":"Sofas","s":false},"56101503":{"n":"Coat racks","s":false},"56101504":{"n":"Chairs","s":false},"56101505":{"n":"Entertainment centers","s":false},"56101506":{"n":"Futons","s":false},"56101507":{"n":"Bookcases","s":false},"56101508":{"n":"Mattresses or sleep sets","s":false},"56101509":{"n":"Dressers or armoires","s":false},"56101510":{"n":"Partitions","s":false},"56101513":{"n":"Cots or accessories","s":false},"56101514":{"n":"Foot stools","s":false},"56101515":{"n":"Beds","s":false},"56101516":{"n":"Chests","s":false},"56101518":{"n":"Wall racks","s":false},"56101519":{"n":"Tables","s":false},"56101520":{"n":"Lockers","s":false},"56101521":{"n":"Bed headboard or footboard","s":false},"56101522":{"n":"Arm chair","s":false},"56101523":{"n":"Umbrella holders or stands","s":false},"56101524":{"n":"Ironing boards","s":false},"56101525":{"n":"Ironing board covers","s":false},"56101526":{"n":"Fridge bar","s":false},"56101527":{"n":"Household type linen driers","s":false},"56101528":{"n":"Artificial plants","s":false},"56101529":{"n":"Magazine or other printed publication rack, container or organizer","s":false},"56101530":{"n":"Storage cabinets","s":false},"56101531":{"n":"Shoe racks","s":false},"56101532":{"n":"Furniture set","s":false},"56101533":{"n":"Armrests","s":false},"56101535":{"n":"Furniture carts","s":false},"56101536":{"n":"Instrument tripods","s":false},"56101537":{"n":"Dressing tables","s":false},"56101538":{"n":"Dining servers or buffets","s":false},"56101539":{"n":"Bedframes or parts or accessories","s":false},"56101540":{"n":"Apparel costumers","s":false},"56101541":{"n":"Mattress ventilators","s":false},"56101542":{"n":"Folding chairs","s":false},"56101543":{"n":"Dining table","s":false},"56101544":{"n":"Furniture mirror","s":false},"56101545":{"n":"Decorative mirror","s":false},"56101546":{"n":"Test bench for furniture","s":false}}},"56101600":{"n":"Outdoor furniture","d":{"56101601":{"n":"Outdoor umbrellas","s":false},"56101602":{"n":"Outdoor chairs","s":false},"56101603":{"n":"Outdoor tables or picnic tables","s":false},"56101604":{"n":"Outdoor swings","s":false},"56101605":{"n":"Outdoor benches","s":false},"56101606":{"n":"Flower stands","s":false},"56101607":{"n":"Outside clothes dryer","s":false},"56101608":{"n":"Bicycle racks","s":false},"56101609":{"n":"Clay flowerpot","s":false},"56101610":{"n":"Flowerpot support","s":false}}},"56101700":{"n":"Office furniture","d":{"56101701":{"n":"Credenzas","s":false},"56101702":{"n":"Filing cabinets or accessories","s":false},"56101703":{"n":"Desks","s":false},"56101704":{"n":"Table base","s":false},"56101705":{"n":"Showcases","s":false},"56101706":{"n":"Conferencing tables","s":false},"56101707":{"n":"Drafting tables","s":false},"56101708":{"n":"Mobile files","s":false},"56101710":{"n":"Projector stands or carts","s":false},"56101711":{"n":"Modular furniture connectors","s":false},"56101712":{"n":"Pedestals","s":false},"56101713":{"n":"Desk returns","s":false},"56101714":{"n":"Data binder racks","s":false},"56101715":{"n":"Mail sorters or organizers","s":false},"56101716":{"n":"Desktop organizer hutches","s":false},"56101717":{"n":"Table risers","s":false},"56101718":{"n":"Newspaper rack","s":false},"56101719":{"n":"Side table","s":false},"56101720":{"n":"Office or work chair","s":false}}},"56101800":{"n":"Baby and toddler furniture and accessories","d":{"56101803":{"n":"Carriages or perambulators or strollers","s":false},"56101804":{"n":"Cribs or playpens or accessories","s":false},"56101805":{"n":"Car seats","s":false},"56101806":{"n":"High chairs or accessories","s":false},"56101807":{"n":"Bouncer seats or jumpers","s":false},"56101808":{"n":"Swings or jumpers or accessories","s":false},"56101809":{"n":"Potty seats","s":false},"56101810":{"n":"Baby baths or tubs","s":false},"56101811":{"n":"Bassinets or cradles","s":false},"56101812":{"n":"Changing tables or accessories","s":false},"56101813":{"n":"Bath seats","s":false}}},"56101900":{"n":"General furniture parts and accessories","d":{"56101901":{"n":"Furniture tops or work surfaces","s":false},"56101902":{"n":"Furniture moving discs","s":false},"56101903":{"n":"Furniture glides or cups or pads","s":false},"56101904":{"n":"Furniture bases or legs or leg extensions","s":false},"56101905":{"n":"Panel assemblies or sections","s":false},"56101906":{"n":"Table extension leafs","s":false},"56101907":{"n":"Slip covers","s":false}}}}},"56110000":{"n":"Commercial and industrial furniture","c":{"56111500":{"n":"Workstations and office packages","d":{"56111501":{"n":"Modular reception office packages","s":false},"56111502":{"n":"Casegood or non modular executive office packages","s":false},"56111503":{"n":"Modular executive office packages","s":false},"56111504":{"n":"Casegood or non modular managerial office packages","s":false},"56111505":{"n":"Modular managerial office packages","s":false},"56111506":{"n":"Casegood or non modular staff office packages","s":false},"56111507":{"n":"Modular staff office packages","s":false},"56111508":{"n":"Casegood or non modular technical office packages","s":false},"56111509":{"n":"Modular technical office packages","s":false},"56111510":{"n":"Casegood or non modular clerical office packages","s":false},"56111511":{"n":"Modular clerical office packages","s":false},"56111512":{"n":"Casegood or non modular reception office packages","s":false},"56111513":{"n":"Conference or non modular room packages","s":false},"56111514":{"n":"Modular counter office packages","s":false}}},"56111600":{"n":"Panel systems","d":{"56111601":{"n":"Screens for panel systems","s":false},"56111602":{"n":"Storage for panel systems","s":false},"56111603":{"n":"Organization for panel systems","s":false},"56111604":{"n":"Work surfaces for panel systems","s":false},"56111605":{"n":"Lighting or power or data components for panel systems","s":false},"56111606":{"n":"Parts or accessories panel systems","s":false}}},"56111700":{"n":"Casegood and non modular systems","d":{"56111701":{"n":"Casegood or non modular desk","s":false},"56111702":{"n":"Casegood or non modular credenza","s":false},"56111703":{"n":"Casegood or non modular storage","s":false},"56111704":{"n":"Casegood or non modular organization","s":false},"56111705":{"n":"Casegood or non modular lighting or power or data components","s":false},"56111706":{"n":"Casegood or non modular parts or accessories","s":false},"56111707":{"n":"Casegood or non modular shelf","s":false}}},"56111800":{"n":"Freestanding furniture","d":{"56111801":{"n":"Freestanding lighting or power or data components","s":false},"56111802":{"n":"Freestanding tables","s":false},"56111803":{"n":"Freestanding storage","s":false},"56111804":{"n":"Freestanding organization","s":false},"56111805":{"n":"Freestanding parts or accessories","s":false},"56111806":{"n":"Swiveling barber chair","s":false}}},"56111900":{"n":"Industrial furniture","d":{"56111901":{"n":"Industrial lighting or power or data components","s":false},"56111902":{"n":"Industrial work surfaces","s":false},"56111903":{"n":"Industrial storage units","s":false},"56111904":{"n":"Industrial organization","s":false},"56111905":{"n":"Industrial parts or accessories","s":false},"56111906":{"n":"Industrial cabinets or drawers or shelving","s":false},"56111907":{"n":"Industrial tool carts","s":false},"56111908":{"n":"Seismic isolation platform","s":false}}},"56112000":{"n":"Computer support furniture","d":{"56112001":{"n":"Computer support lighting or power or data components","s":false},"56112002":{"n":"Computer support work surfaces","s":false},"56112003":{"n":"Computer support storage accessories","s":false},"56112004":{"n":"Computer support organization","s":false},"56112005":{"n":"Computer support parts or accessories","s":false}}},"56112100":{"n":"Seating","d":{"56112101":{"n":"Auditorium or stadium or special use seating","s":false},"56112102":{"n":"Task seating","s":false},"56112103":{"n":"Guest seating","s":false},"56112104":{"n":"Executive seating","s":false},"56112105":{"n":"Lounge seating","s":false},"56112106":{"n":"Stool seating","s":false},"56112107":{"n":"Seating parts or accessories","s":false},"56112108":{"n":"Combination chair with desk","s":false},"56112109":{"n":"Benches","s":false},"56112110":{"n":"Musician seating","s":false},"56112111":{"n":"Booster seats","s":false}}},"56112200":{"n":"Desking systems","d":{"56112201":{"n":"Desk based screens","s":false},"56112202":{"n":"Desk storage components","s":false},"56112203":{"n":"Desking organizational components","s":false},"56112204":{"n":"Worksurfaces","s":false},"56112205":{"n":"Lighting, power or data components","s":false},"56112206":{"n":"Desking systems related parts and accessories","s":false}}},"56112300":{"n":"Auditorium or stadium or special use seating parts and accessories","d":{"56112301":{"n":"Back rest","s":false},"56112302":{"n":"Footboard seating fixture","s":false},"56112303":{"n":"Seat pivot","s":false},"56112304":{"n":"Chair seat","s":false}}}}},"56120000":{"n":"Classroom and instructional and institutional furniture and fixtures","c":{"56121000":{"n":"Library furnishings","d":{"56121001":{"n":"Book carts or book trucks","s":false},"56121002":{"n":"Circulation or librarian desks or components","s":false},"56121003":{"n":"Book returns","s":false},"56121004":{"n":"Card catalog units","s":false},"56121005":{"n":"Dictionary stands","s":false},"56121006":{"n":"Upholstered benches","s":false},"56121007":{"n":"Public access tables","s":false},"56121008":{"n":"Book browser units","s":false},"56121009":{"n":"Sloped reading tables","s":false},"56121010":{"n":"Book kiosks","s":false},"56121011":{"n":"Library compact disc or audio cassette displayers","s":false},"56121012":{"n":"Rotary island stands","s":false},"56121014":{"n":"Hang up bag racks or bags","s":false},"56121015":{"n":"Mobile book rack","s":false}}},"56121100":{"n":"Art classroom furnishings","d":{"56121101":{"n":"Art horse","s":false},"56121102":{"n":"Art student bench","s":false}}},"56121200":{"n":"First aid room furnishings","d":{"56121201":{"n":"First aid couches","s":false}}},"56121300":{"n":"General educational facility fixtures","d":{"56121301":{"n":"Standing risers","s":false},"56121302":{"n":"Table or chair movers or caddys","s":false},"56121303":{"n":"Rubber brush floor matting","s":false},"56121304":{"n":"Planning tables","s":false}}},"56121400":{"n":"Cafeteria and lunchroom furnishings","d":{"56121401":{"n":"Mobile bench tables","s":false},"56121402":{"n":"Mobile stool tables","s":false},"56121403":{"n":"Mobile tables","s":false}}},"56121500":{"n":"General classroom furnishings","d":{"56121501":{"n":"Activity tables","s":false},"56121502":{"n":"Classroom chairs","s":false},"56121503":{"n":"Classroom benches","s":false},"56121504":{"n":"Classroom stools","s":false},"56121505":{"n":"Classroom tables","s":false},"56121506":{"n":"Student desks","s":false},"56121507":{"n":"Study carrels","s":false},"56121508":{"n":"Student computer desks","s":false},"56121509":{"n":"Student computer tables","s":false},"56121510":{"n":"Teacher desk","s":false}}},"56121600":{"n":"Creative play and rest time furnishings for daycare and early childhood facilities","d":{"56121601":{"n":"Toddler or child size living room sets","s":false},"56121602":{"n":"Toddler or child size sofas","s":false},"56121603":{"n":"Toddler or child size easy chairs","s":false},"56121604":{"n":"Toddler or child size bean bag chairs","s":false},"56121605":{"n":"Low rise room dividers or play panels","s":false},"56121606":{"n":"Childs rest mats","s":false},"56121607":{"n":"Childs rest mat racks or holders","s":false},"56121608":{"n":"Childrens cots","s":false},"56121609":{"n":"Childrens cot carriers","s":false},"56121610":{"n":"Childrens cot activity systems","s":false},"56121611":{"n":"Infant table","s":false}}},"56121700":{"n":"Book and general storage units for classrooms","d":{"56121701":{"n":"General storage units","s":false},"56121702":{"n":"Book storage units","s":false},"56121703":{"n":"Cubbie units","s":false},"56121704":{"n":"Institutional Storage Cabinets","s":false}}},"56121800":{"n":"Vocational classroom furnishings and fixtures","d":{"56121801":{"n":"Technical education tool storage cabinets or cabinets with tools","s":false},"56121802":{"n":"General shop tool storage cabinets or cabinets with tools","s":false},"56121803":{"n":"Woodworking tool storage cabinets or cabinets with tools","s":false},"56121804":{"n":"Instructors technical desk","s":false},"56121805":{"n":"Flat files","s":false}}},"56121900":{"n":"Demonstration furnishings","d":{"56121901":{"n":"Sewing machine demonstrator tables","s":false},"56121902":{"n":"Display stand","s":false},"56121903":{"n":"Relic preservation storage cabinet","s":false}}},"56122000":{"n":"Laboratory furniture","d":{"56122001":{"n":"Laboratory benches","s":false},"56122002":{"n":"Laboratory storage units or accessories","s":false},"56122003":{"n":"Laboratory workstations","s":false},"56122004":{"n":"Sink base units","s":false}}}}},"56130000":{"n":"Merchandising furniture and accessories","c":{"56131500":{"n":"Mannequins and forms","d":{"56131501":{"n":"Bust forms","s":false},"56131502":{"n":"Head forms","s":false},"56131503":{"n":"Neck forms","s":false},"56131504":{"n":"Full body form or mannequin","s":false}}},"56131600":{"n":"Merchandiser free standing display and accessories","d":{"56131601":{"n":"Floor stands","s":false},"56131602":{"n":"Free standing display poles","s":false},"56131603":{"n":"Sales counters","s":false},"56131604":{"n":"Paint color center component","s":false},"56131605":{"n":"Paint chain board","s":false},"56131606":{"n":"Paint color fan deck","s":false},"56131607":{"n":"Color inspiration selection","s":false}}},"56131700":{"n":"Merchandiser installation hardware, shelving systems and accessories","d":{"56131701":{"n":"Hang rails","s":false},"56131702":{"n":"Merchandise baskets","s":false},"56131703":{"n":"Waterfalls or straight arm face outs","s":false}}}}},"56140000":{"n":"Decorative adornments","c":{"56141500":{"n":"Ceramic adornments","d":{"56141501":{"n":"Ceramic bowl","s":false},"56141502":{"n":"Ceramic plate or platter","s":false},"56141503":{"n":"Ceramic vase","s":false},"56141504":{"n":"Ceramic statuette or figurine","s":false}}},"56141600":{"n":"Glass adornments","d":{"56141601":{"n":"Glass bowl","s":false},"56141602":{"n":"Glass vase","s":false},"56141603":{"n":"Glass plate or platter","s":false},"56141604":{"n":"Glass statuette or figurine","s":false}}},"56141700":{"n":"Metal adornments","d":{"56141701":{"n":"Metal bowl","s":false},"56141702":{"n":"Metal chest or box","s":false},"56141703":{"n":"Metal figurine or statuette","s":false},"56141704":{"n":"Metal vase","s":false},"56141705":{"n":"Decorative metal utensils","s":false},"56141706":{"n":"Decorative metal plate","s":false}}},"56141800":{"n":"Wooden adornments","d":{"56141801":{"n":"Wooden bowl","s":false},"56141802":{"n":"Wooden chest or box","s":false},"56141803":{"n":"Wooden figurine or statuette","s":false},"56141804":{"n":"Decorative wooden utensils","s":false},"56141805":{"n":"Wooden vase","s":false},"56141806":{"n":"Decorative wooden plate or tray","s":false}}}}}}}